{
 "cells": [
  {
   "cell_type": "code",
   "execution_count": 68,
   "id": "a26eb2e8",
   "metadata": {},
   "outputs": [],
   "source": [
    "#Set up the environment\n",
    "import pandas as pd\n",
    "\n",
    "import numpy as np"
   ]
  },
  {
   "cell_type": "code",
   "execution_count": 69,
   "id": "e5c8b457",
   "metadata": {},
   "outputs": [],
   "source": [
    "#Import data\n",
    "df = pd.read_csv(\"documents/housemodifiedrent.csv\")"
   ]
  },
  {
   "cell_type": "code",
   "execution_count": 70,
   "id": "ae14b7d4",
   "metadata": {},
   "outputs": [
    {
     "data": {
      "text/html": [
       "<div>\n",
       "<style scoped>\n",
       "    .dataframe tbody tr th:only-of-type {\n",
       "        vertical-align: middle;\n",
       "    }\n",
       "\n",
       "    .dataframe tbody tr th {\n",
       "        vertical-align: top;\n",
       "    }\n",
       "\n",
       "    .dataframe thead th {\n",
       "        text-align: right;\n",
       "    }\n",
       "</style>\n",
       "<table border=\"1\" class=\"dataframe\">\n",
       "  <thead>\n",
       "    <tr style=\"text-align: right;\">\n",
       "      <th></th>\n",
       "      <th>Floor Level Updated</th>\n",
       "      <th>Floor Total</th>\n",
       "      <th>Posted On</th>\n",
       "      <th>BHK</th>\n",
       "      <th>Rent</th>\n",
       "      <th>Size</th>\n",
       "      <th>Floor</th>\n",
       "      <th>Area Type</th>\n",
       "      <th>Area Locality</th>\n",
       "      <th>City</th>\n",
       "      <th>Furnishing Status</th>\n",
       "      <th>Tenant Preferred</th>\n",
       "      <th>Bathrooms</th>\n",
       "      <th>Point of Contact</th>\n",
       "    </tr>\n",
       "  </thead>\n",
       "  <tbody>\n",
       "    <tr>\n",
       "      <th>0</th>\n",
       "      <td>0.0</td>\n",
       "      <td>2</td>\n",
       "      <td>5/18/2022</td>\n",
       "      <td>2</td>\n",
       "      <td>10000</td>\n",
       "      <td>1100</td>\n",
       "      <td>Ground out of 2</td>\n",
       "      <td>Super Area</td>\n",
       "      <td>Bandel</td>\n",
       "      <td>Kolkata</td>\n",
       "      <td>Unfurnished</td>\n",
       "      <td>No Preference</td>\n",
       "      <td>2</td>\n",
       "      <td>Contact Owner</td>\n",
       "    </tr>\n",
       "    <tr>\n",
       "      <th>1</th>\n",
       "      <td>1.0</td>\n",
       "      <td>3</td>\n",
       "      <td>5/13/2022</td>\n",
       "      <td>2</td>\n",
       "      <td>20000</td>\n",
       "      <td>800</td>\n",
       "      <td>1 out of 3</td>\n",
       "      <td>Super Area</td>\n",
       "      <td>Phool Bagan, Kankurgachi</td>\n",
       "      <td>Kolkata</td>\n",
       "      <td>Semi-Furnished</td>\n",
       "      <td>No Preference</td>\n",
       "      <td>1</td>\n",
       "      <td>Contact Owner</td>\n",
       "    </tr>\n",
       "    <tr>\n",
       "      <th>2</th>\n",
       "      <td>1.0</td>\n",
       "      <td>3</td>\n",
       "      <td>5/16/2022</td>\n",
       "      <td>2</td>\n",
       "      <td>17000</td>\n",
       "      <td>1000</td>\n",
       "      <td>1 out of 3</td>\n",
       "      <td>Super Area</td>\n",
       "      <td>Salt Lake City Sector 2</td>\n",
       "      <td>Kolkata</td>\n",
       "      <td>Semi-Furnished</td>\n",
       "      <td>No Preference</td>\n",
       "      <td>1</td>\n",
       "      <td>Contact Owner</td>\n",
       "    </tr>\n",
       "    <tr>\n",
       "      <th>3</th>\n",
       "      <td>1.0</td>\n",
       "      <td>2</td>\n",
       "      <td>7/4/2022</td>\n",
       "      <td>2</td>\n",
       "      <td>10000</td>\n",
       "      <td>800</td>\n",
       "      <td>1 out of 2</td>\n",
       "      <td>Super Area</td>\n",
       "      <td>Dumdum Park</td>\n",
       "      <td>Kolkata</td>\n",
       "      <td>Unfurnished</td>\n",
       "      <td>No Preference</td>\n",
       "      <td>1</td>\n",
       "      <td>Contact Owner</td>\n",
       "    </tr>\n",
       "    <tr>\n",
       "      <th>4</th>\n",
       "      <td>1.0</td>\n",
       "      <td>2</td>\n",
       "      <td>5/9/2022</td>\n",
       "      <td>2</td>\n",
       "      <td>7500</td>\n",
       "      <td>850</td>\n",
       "      <td>1 out of 2</td>\n",
       "      <td>Carpet Area</td>\n",
       "      <td>South Dum Dum</td>\n",
       "      <td>Kolkata</td>\n",
       "      <td>Unfurnished</td>\n",
       "      <td>Bachelors</td>\n",
       "      <td>1</td>\n",
       "      <td>Contact Owner</td>\n",
       "    </tr>\n",
       "    <tr>\n",
       "      <th>5</th>\n",
       "      <td>0.0</td>\n",
       "      <td>1</td>\n",
       "      <td>4/29/2022</td>\n",
       "      <td>2</td>\n",
       "      <td>7000</td>\n",
       "      <td>600</td>\n",
       "      <td>Ground out of 1</td>\n",
       "      <td>Super Area</td>\n",
       "      <td>Thakurpukur</td>\n",
       "      <td>Kolkata</td>\n",
       "      <td>Unfurnished</td>\n",
       "      <td>No Preference</td>\n",
       "      <td>2</td>\n",
       "      <td>Contact Owner</td>\n",
       "    </tr>\n",
       "    <tr>\n",
       "      <th>6</th>\n",
       "      <td>0.0</td>\n",
       "      <td>4</td>\n",
       "      <td>6/21/2022</td>\n",
       "      <td>2</td>\n",
       "      <td>10000</td>\n",
       "      <td>700</td>\n",
       "      <td>Ground out of 4</td>\n",
       "      <td>Super Area</td>\n",
       "      <td>Malancha</td>\n",
       "      <td>Kolkata</td>\n",
       "      <td>Unfurnished</td>\n",
       "      <td>Bachelors</td>\n",
       "      <td>2</td>\n",
       "      <td>Contact Agent</td>\n",
       "    </tr>\n",
       "    <tr>\n",
       "      <th>7</th>\n",
       "      <td>1.0</td>\n",
       "      <td>2</td>\n",
       "      <td>6/21/2022</td>\n",
       "      <td>1</td>\n",
       "      <td>5000</td>\n",
       "      <td>250</td>\n",
       "      <td>1 out of 2</td>\n",
       "      <td>Super Area</td>\n",
       "      <td>Malancha</td>\n",
       "      <td>Kolkata</td>\n",
       "      <td>Unfurnished</td>\n",
       "      <td>Bachelors</td>\n",
       "      <td>1</td>\n",
       "      <td>Contact Agent</td>\n",
       "    </tr>\n",
       "    <tr>\n",
       "      <th>8</th>\n",
       "      <td>1.0</td>\n",
       "      <td>2</td>\n",
       "      <td>6/7/2022</td>\n",
       "      <td>2</td>\n",
       "      <td>26000</td>\n",
       "      <td>800</td>\n",
       "      <td>1 out of 2</td>\n",
       "      <td>Carpet Area</td>\n",
       "      <td>Palm Avenue Kolkata, Ballygunge</td>\n",
       "      <td>Kolkata</td>\n",
       "      <td>Unfurnished</td>\n",
       "      <td>Bachelors</td>\n",
       "      <td>2</td>\n",
       "      <td>Contact Agent</td>\n",
       "    </tr>\n",
       "    <tr>\n",
       "      <th>9</th>\n",
       "      <td>1.0</td>\n",
       "      <td>3</td>\n",
       "      <td>6/20/2022</td>\n",
       "      <td>2</td>\n",
       "      <td>10000</td>\n",
       "      <td>1000</td>\n",
       "      <td>1 out of 3</td>\n",
       "      <td>Carpet Area</td>\n",
       "      <td>Natunhat</td>\n",
       "      <td>Kolkata</td>\n",
       "      <td>Semi-Furnished</td>\n",
       "      <td>No Preference</td>\n",
       "      <td>2</td>\n",
       "      <td>Contact Owner</td>\n",
       "    </tr>\n",
       "  </tbody>\n",
       "</table>\n",
       "</div>"
      ],
      "text/plain": [
       "   Floor Level Updated Floor Total  Posted On  BHK   Rent  Size  \\\n",
       "0                  0.0           2  5/18/2022    2  10000  1100   \n",
       "1                  1.0           3  5/13/2022    2  20000   800   \n",
       "2                  1.0           3  5/16/2022    2  17000  1000   \n",
       "3                  1.0           2   7/4/2022    2  10000   800   \n",
       "4                  1.0           2   5/9/2022    2   7500   850   \n",
       "5                  0.0           1  4/29/2022    2   7000   600   \n",
       "6                  0.0           4  6/21/2022    2  10000   700   \n",
       "7                  1.0           2  6/21/2022    1   5000   250   \n",
       "8                  1.0           2   6/7/2022    2  26000   800   \n",
       "9                  1.0           3  6/20/2022    2  10000  1000   \n",
       "\n",
       "             Floor    Area Type                    Area Locality     City  \\\n",
       "0  Ground out of 2   Super Area                           Bandel  Kolkata   \n",
       "1       1 out of 3   Super Area         Phool Bagan, Kankurgachi  Kolkata   \n",
       "2       1 out of 3   Super Area          Salt Lake City Sector 2  Kolkata   \n",
       "3       1 out of 2   Super Area                      Dumdum Park  Kolkata   \n",
       "4       1 out of 2  Carpet Area                    South Dum Dum  Kolkata   \n",
       "5  Ground out of 1   Super Area                      Thakurpukur  Kolkata   \n",
       "6  Ground out of 4   Super Area                         Malancha  Kolkata   \n",
       "7       1 out of 2   Super Area                         Malancha  Kolkata   \n",
       "8       1 out of 2  Carpet Area  Palm Avenue Kolkata, Ballygunge  Kolkata   \n",
       "9       1 out of 3  Carpet Area                         Natunhat  Kolkata   \n",
       "\n",
       "  Furnishing Status Tenant Preferred  Bathrooms Point of Contact  \n",
       "0       Unfurnished    No Preference          2    Contact Owner  \n",
       "1    Semi-Furnished    No Preference          1    Contact Owner  \n",
       "2    Semi-Furnished    No Preference          1    Contact Owner  \n",
       "3       Unfurnished    No Preference          1    Contact Owner  \n",
       "4       Unfurnished        Bachelors          1    Contact Owner  \n",
       "5       Unfurnished    No Preference          2    Contact Owner  \n",
       "6       Unfurnished        Bachelors          2    Contact Agent  \n",
       "7       Unfurnished        Bachelors          1    Contact Agent  \n",
       "8       Unfurnished        Bachelors          2    Contact Agent  \n",
       "9    Semi-Furnished    No Preference          2    Contact Owner  "
      ]
     },
     "execution_count": 70,
     "metadata": {},
     "output_type": "execute_result"
    }
   ],
   "source": [
    "df.head(10)"
   ]
  },
  {
   "cell_type": "code",
   "execution_count": 71,
   "id": "3092ce12",
   "metadata": {},
   "outputs": [
    {
     "data": {
      "text/html": [
       "<div>\n",
       "<style scoped>\n",
       "    .dataframe tbody tr th:only-of-type {\n",
       "        vertical-align: middle;\n",
       "    }\n",
       "\n",
       "    .dataframe tbody tr th {\n",
       "        vertical-align: top;\n",
       "    }\n",
       "\n",
       "    .dataframe thead th {\n",
       "        text-align: right;\n",
       "    }\n",
       "</style>\n",
       "<table border=\"1\" class=\"dataframe\">\n",
       "  <thead>\n",
       "    <tr style=\"text-align: right;\">\n",
       "      <th></th>\n",
       "      <th>Floor Level Updated</th>\n",
       "      <th>Floor Total</th>\n",
       "      <th>Posted On</th>\n",
       "      <th>BHK</th>\n",
       "      <th>Rent</th>\n",
       "      <th>Size</th>\n",
       "      <th>Floor</th>\n",
       "      <th>Area Type</th>\n",
       "      <th>Area Locality</th>\n",
       "      <th>City</th>\n",
       "      <th>Furnishing Status</th>\n",
       "      <th>Tenant Preferred</th>\n",
       "      <th>Bathrooms</th>\n",
       "      <th>Point of Contact</th>\n",
       "    </tr>\n",
       "  </thead>\n",
       "  <tbody>\n",
       "    <tr>\n",
       "      <th>4736</th>\n",
       "      <td>NaN</td>\n",
       "      <td>2</td>\n",
       "      <td>6/28/2022</td>\n",
       "      <td>3</td>\n",
       "      <td>15000</td>\n",
       "      <td>1500</td>\n",
       "      <td>Lower Basement out of 2</td>\n",
       "      <td>Super Area</td>\n",
       "      <td>Almasguda</td>\n",
       "      <td>Hyderabad</td>\n",
       "      <td>Semi-Furnished</td>\n",
       "      <td>Family</td>\n",
       "      <td>3</td>\n",
       "      <td>Contact Owner</td>\n",
       "    </tr>\n",
       "    <tr>\n",
       "      <th>4737</th>\n",
       "      <td>NaN</td>\n",
       "      <td>2</td>\n",
       "      <td>7/7/2022</td>\n",
       "      <td>3</td>\n",
       "      <td>15000</td>\n",
       "      <td>1500</td>\n",
       "      <td>Lower Basement out of 2</td>\n",
       "      <td>Super Area</td>\n",
       "      <td>Almasguda</td>\n",
       "      <td>Hyderabad</td>\n",
       "      <td>Semi-Furnished</td>\n",
       "      <td>No Preference</td>\n",
       "      <td>3</td>\n",
       "      <td>Contact Owner</td>\n",
       "    </tr>\n",
       "    <tr>\n",
       "      <th>4738</th>\n",
       "      <td>4.0</td>\n",
       "      <td>5</td>\n",
       "      <td>7/6/2022</td>\n",
       "      <td>2</td>\n",
       "      <td>17000</td>\n",
       "      <td>855</td>\n",
       "      <td>4 out of 5</td>\n",
       "      <td>Carpet Area</td>\n",
       "      <td>Godavari Homes, Quthbullapur</td>\n",
       "      <td>Hyderabad</td>\n",
       "      <td>Unfurnished</td>\n",
       "      <td>Bachelors</td>\n",
       "      <td>2</td>\n",
       "      <td>Contact Agent</td>\n",
       "    </tr>\n",
       "    <tr>\n",
       "      <th>4739</th>\n",
       "      <td>2.0</td>\n",
       "      <td>4</td>\n",
       "      <td>7/6/2022</td>\n",
       "      <td>2</td>\n",
       "      <td>25000</td>\n",
       "      <td>1040</td>\n",
       "      <td>2 out of 4</td>\n",
       "      <td>Carpet Area</td>\n",
       "      <td>Gachibowli</td>\n",
       "      <td>Hyderabad</td>\n",
       "      <td>Unfurnished</td>\n",
       "      <td>Bachelors</td>\n",
       "      <td>2</td>\n",
       "      <td>Contact Owner</td>\n",
       "    </tr>\n",
       "    <tr>\n",
       "      <th>4740</th>\n",
       "      <td>2.0</td>\n",
       "      <td>2</td>\n",
       "      <td>6/2/2022</td>\n",
       "      <td>2</td>\n",
       "      <td>12000</td>\n",
       "      <td>1350</td>\n",
       "      <td>2 out of 2</td>\n",
       "      <td>Super Area</td>\n",
       "      <td>Old Alwal</td>\n",
       "      <td>Hyderabad</td>\n",
       "      <td>Unfurnished</td>\n",
       "      <td>No Preference</td>\n",
       "      <td>2</td>\n",
       "      <td>Contact Owner</td>\n",
       "    </tr>\n",
       "    <tr>\n",
       "      <th>4741</th>\n",
       "      <td>3.0</td>\n",
       "      <td>5</td>\n",
       "      <td>5/18/2022</td>\n",
       "      <td>2</td>\n",
       "      <td>15000</td>\n",
       "      <td>1000</td>\n",
       "      <td>3 out of 5</td>\n",
       "      <td>Carpet Area</td>\n",
       "      <td>Bandam Kommu</td>\n",
       "      <td>Hyderabad</td>\n",
       "      <td>Semi-Furnished</td>\n",
       "      <td>No Preference</td>\n",
       "      <td>2</td>\n",
       "      <td>Contact Owner</td>\n",
       "    </tr>\n",
       "    <tr>\n",
       "      <th>4742</th>\n",
       "      <td>1.0</td>\n",
       "      <td>4</td>\n",
       "      <td>5/15/2022</td>\n",
       "      <td>3</td>\n",
       "      <td>29000</td>\n",
       "      <td>2000</td>\n",
       "      <td>1 out of 4</td>\n",
       "      <td>Super Area</td>\n",
       "      <td>Manikonda, Hyderabad</td>\n",
       "      <td>Hyderabad</td>\n",
       "      <td>Semi-Furnished</td>\n",
       "      <td>No Preference</td>\n",
       "      <td>3</td>\n",
       "      <td>Contact Owner</td>\n",
       "    </tr>\n",
       "    <tr>\n",
       "      <th>4743</th>\n",
       "      <td>3.0</td>\n",
       "      <td>5</td>\n",
       "      <td>7/10/2022</td>\n",
       "      <td>3</td>\n",
       "      <td>35000</td>\n",
       "      <td>1750</td>\n",
       "      <td>3 out of 5</td>\n",
       "      <td>Carpet Area</td>\n",
       "      <td>Himayath Nagar, NH 7</td>\n",
       "      <td>Hyderabad</td>\n",
       "      <td>Semi-Furnished</td>\n",
       "      <td>No Preference</td>\n",
       "      <td>3</td>\n",
       "      <td>Contact Agent</td>\n",
       "    </tr>\n",
       "    <tr>\n",
       "      <th>4744</th>\n",
       "      <td>23.0</td>\n",
       "      <td>34</td>\n",
       "      <td>7/6/2022</td>\n",
       "      <td>3</td>\n",
       "      <td>45000</td>\n",
       "      <td>1500</td>\n",
       "      <td>23 out of 34</td>\n",
       "      <td>Carpet Area</td>\n",
       "      <td>Gachibowli</td>\n",
       "      <td>Hyderabad</td>\n",
       "      <td>Semi-Furnished</td>\n",
       "      <td>Family</td>\n",
       "      <td>2</td>\n",
       "      <td>Contact Agent</td>\n",
       "    </tr>\n",
       "    <tr>\n",
       "      <th>4745</th>\n",
       "      <td>4.0</td>\n",
       "      <td>5</td>\n",
       "      <td>5/4/2022</td>\n",
       "      <td>2</td>\n",
       "      <td>15000</td>\n",
       "      <td>1000</td>\n",
       "      <td>4 out of 5</td>\n",
       "      <td>Carpet Area</td>\n",
       "      <td>Suchitra Circle</td>\n",
       "      <td>Hyderabad</td>\n",
       "      <td>Unfurnished</td>\n",
       "      <td>Bachelors</td>\n",
       "      <td>2</td>\n",
       "      <td>Contact Owner</td>\n",
       "    </tr>\n",
       "  </tbody>\n",
       "</table>\n",
       "</div>"
      ],
      "text/plain": [
       "      Floor Level Updated Floor Total  Posted On  BHK   Rent  Size  \\\n",
       "4736                  NaN           2  6/28/2022    3  15000  1500   \n",
       "4737                  NaN           2   7/7/2022    3  15000  1500   \n",
       "4738                  4.0           5   7/6/2022    2  17000   855   \n",
       "4739                  2.0           4   7/6/2022    2  25000  1040   \n",
       "4740                  2.0           2   6/2/2022    2  12000  1350   \n",
       "4741                  3.0           5  5/18/2022    2  15000  1000   \n",
       "4742                  1.0           4  5/15/2022    3  29000  2000   \n",
       "4743                  3.0           5  7/10/2022    3  35000  1750   \n",
       "4744                 23.0          34   7/6/2022    3  45000  1500   \n",
       "4745                  4.0           5   5/4/2022    2  15000  1000   \n",
       "\n",
       "                        Floor    Area Type                 Area Locality  \\\n",
       "4736  Lower Basement out of 2   Super Area                     Almasguda   \n",
       "4737  Lower Basement out of 2   Super Area                     Almasguda   \n",
       "4738               4 out of 5  Carpet Area  Godavari Homes, Quthbullapur   \n",
       "4739               2 out of 4  Carpet Area                    Gachibowli   \n",
       "4740               2 out of 2   Super Area                     Old Alwal   \n",
       "4741               3 out of 5  Carpet Area                  Bandam Kommu   \n",
       "4742               1 out of 4   Super Area          Manikonda, Hyderabad   \n",
       "4743               3 out of 5  Carpet Area          Himayath Nagar, NH 7   \n",
       "4744             23 out of 34  Carpet Area                    Gachibowli   \n",
       "4745               4 out of 5  Carpet Area               Suchitra Circle   \n",
       "\n",
       "           City Furnishing Status Tenant Preferred  Bathrooms Point of Contact  \n",
       "4736  Hyderabad    Semi-Furnished           Family          3    Contact Owner  \n",
       "4737  Hyderabad    Semi-Furnished    No Preference          3    Contact Owner  \n",
       "4738  Hyderabad       Unfurnished        Bachelors          2    Contact Agent  \n",
       "4739  Hyderabad       Unfurnished        Bachelors          2    Contact Owner  \n",
       "4740  Hyderabad       Unfurnished    No Preference          2    Contact Owner  \n",
       "4741  Hyderabad    Semi-Furnished    No Preference          2    Contact Owner  \n",
       "4742  Hyderabad    Semi-Furnished    No Preference          3    Contact Owner  \n",
       "4743  Hyderabad    Semi-Furnished    No Preference          3    Contact Agent  \n",
       "4744  Hyderabad    Semi-Furnished           Family          2    Contact Agent  \n",
       "4745  Hyderabad       Unfurnished        Bachelors          2    Contact Owner  "
      ]
     },
     "execution_count": 71,
     "metadata": {},
     "output_type": "execute_result"
    }
   ],
   "source": [
    "df.tail(10)"
   ]
  },
  {
   "cell_type": "markdown",
   "id": "a679ee41",
   "metadata": {},
   "source": [
    "Above, there are some missing values within the data. We will look at whether there are other NaaN values in other columns."
   ]
  },
  {
   "cell_type": "code",
   "execution_count": 72,
   "id": "58924668",
   "metadata": {},
   "outputs": [
    {
     "data": {
      "text/plain": [
       "Floor Level Updated    34\n",
       "Floor Total             0\n",
       "Posted On               0\n",
       "BHK                     0\n",
       "Rent                    0\n",
       "Size                    0\n",
       "Floor                   0\n",
       "Area Type               0\n",
       "Area Locality           0\n",
       "City                    0\n",
       "Furnishing Status       0\n",
       "Tenant Preferred        0\n",
       "Bathrooms               0\n",
       "Point of Contact        0\n",
       "dtype: int64"
      ]
     },
     "execution_count": 72,
     "metadata": {},
     "output_type": "execute_result"
    }
   ],
   "source": [
    "df.isna().sum()"
   ]
  },
  {
   "cell_type": "markdown",
   "id": "6f4c8f10",
   "metadata": {},
   "source": [
    "There are 34 missing values in the Floor Level Updated column. \n",
    "\n",
    "There are different ways we can deal with this problem.\n",
    "\n",
    "1. We can get rid of the null values\n",
    "2. Fill in those values since we know there is 34 NaaN values"
   ]
  },
  {
   "cell_type": "code",
   "execution_count": 73,
   "id": "f383e4a8",
   "metadata": {},
   "outputs": [],
   "source": [
    "df['Floor Level Updated'].fillna(df['Floor'], inplace=True)\n"
   ]
  },
  {
   "cell_type": "code",
   "execution_count": 74,
   "id": "f712c72e",
   "metadata": {},
   "outputs": [
    {
     "data": {
      "text/plain": [
       "Floor Level Updated    0\n",
       "Floor Total            0\n",
       "Posted On              0\n",
       "BHK                    0\n",
       "Rent                   0\n",
       "Size                   0\n",
       "Floor                  0\n",
       "Area Type              0\n",
       "Area Locality          0\n",
       "City                   0\n",
       "Furnishing Status      0\n",
       "Tenant Preferred       0\n",
       "Bathrooms              0\n",
       "Point of Contact       0\n",
       "dtype: int64"
      ]
     },
     "execution_count": 74,
     "metadata": {},
     "output_type": "execute_result"
    }
   ],
   "source": [
    "df.isna().sum()"
   ]
  },
  {
   "cell_type": "markdown",
   "id": "812a4bc5",
   "metadata": {},
   "source": [
    "As you can see above, now there are none null values. Now we move onto whether we need to change any datatypes for these columns or not."
   ]
  },
  {
   "cell_type": "code",
   "execution_count": 75,
   "id": "eab1351d",
   "metadata": {},
   "outputs": [
    {
     "data": {
      "text/plain": [
       "Floor Level Updated    object\n",
       "Floor Total            object\n",
       "Posted On              object\n",
       "BHK                     int64\n",
       "Rent                    int64\n",
       "Size                    int64\n",
       "Floor                  object\n",
       "Area Type              object\n",
       "Area Locality          object\n",
       "City                   object\n",
       "Furnishing Status      object\n",
       "Tenant Preferred       object\n",
       "Bathrooms               int64\n",
       "Point of Contact       object\n",
       "dtype: object"
      ]
     },
     "execution_count": 75,
     "metadata": {},
     "output_type": "execute_result"
    }
   ],
   "source": [
    "df.dtypes"
   ]
  },
  {
   "cell_type": "markdown",
   "id": "310c69b6",
   "metadata": {},
   "source": [
    "We see that Floor Level Updated, Floor Total, Posted On, and Floor should have different datatypes since they are numerical. "
   ]
  },
  {
   "cell_type": "markdown",
   "id": "bfa51e25",
   "metadata": {},
   "source": [
    "Let's start with the Posted On column and change it to datetime."
   ]
  },
  {
   "cell_type": "code",
   "execution_count": 76,
   "id": "6c38e6cc",
   "metadata": {},
   "outputs": [],
   "source": [
    "df['Posted On'] = pd.to_datetime(df['Posted On'])"
   ]
  },
  {
   "cell_type": "markdown",
   "id": "45673bdb",
   "metadata": {},
   "source": [
    "Now let's add the floor columns and change them to int."
   ]
  },
  {
   "cell_type": "code",
   "execution_count": 77,
   "id": "dde507be",
   "metadata": {},
   "outputs": [],
   "source": [
    "df['Floor'] = df['Floor'].apply(pd.to_numeric, errors='coerce').fillna(0.0)\n"
   ]
  },
  {
   "cell_type": "code",
   "execution_count": 78,
   "id": "e08a08d5",
   "metadata": {},
   "outputs": [],
   "source": [
    "df['Floor Total'] = df['Floor Total'].apply(pd.to_numeric, errors='coerce').fillna(0.0)\n"
   ]
  },
  {
   "cell_type": "code",
   "execution_count": 79,
   "id": "b870a80e",
   "metadata": {},
   "outputs": [],
   "source": [
    "df['Floor Level Updated'] = df['Floor Level Updated'].apply(pd.to_numeric, errors='coerce').fillna(0.0)\n"
   ]
  },
  {
   "cell_type": "code",
   "execution_count": 80,
   "id": "a533489a",
   "metadata": {},
   "outputs": [
    {
     "data": {
      "text/plain": [
       "Floor Level Updated           float64\n",
       "Floor Total                   float64\n",
       "Posted On              datetime64[ns]\n",
       "BHK                             int64\n",
       "Rent                            int64\n",
       "Size                            int64\n",
       "Floor                         float64\n",
       "Area Type                      object\n",
       "Area Locality                  object\n",
       "City                           object\n",
       "Furnishing Status              object\n",
       "Tenant Preferred               object\n",
       "Bathrooms                       int64\n",
       "Point of Contact               object\n",
       "dtype: object"
      ]
     },
     "execution_count": 80,
     "metadata": {},
     "output_type": "execute_result"
    }
   ],
   "source": [
    "df.dtypes"
   ]
  },
  {
   "cell_type": "markdown",
   "id": "091fb30e",
   "metadata": {},
   "source": [
    "The code above for the floor columns did these two things:\n",
    "1. Convert all column types to numeric types, fill in NaN for errors, and fill in 0 for NaNs\n",
    "\n",
    "2. The column of object is converted to float\n",
    "\n",
    "Now we move onto the basic descriptive analysis!"
   ]
  },
  {
   "cell_type": "code",
   "execution_count": 81,
   "id": "bfa2ff53",
   "metadata": {},
   "outputs": [
    {
     "data": {
      "text/html": [
       "<div>\n",
       "<style scoped>\n",
       "    .dataframe tbody tr th:only-of-type {\n",
       "        vertical-align: middle;\n",
       "    }\n",
       "\n",
       "    .dataframe tbody tr th {\n",
       "        vertical-align: top;\n",
       "    }\n",
       "\n",
       "    .dataframe thead th {\n",
       "        text-align: right;\n",
       "    }\n",
       "</style>\n",
       "<table border=\"1\" class=\"dataframe\">\n",
       "  <thead>\n",
       "    <tr style=\"text-align: right;\">\n",
       "      <th></th>\n",
       "      <th>count</th>\n",
       "      <th>mean</th>\n",
       "      <th>std</th>\n",
       "      <th>min</th>\n",
       "      <th>25%</th>\n",
       "      <th>50%</th>\n",
       "      <th>75%</th>\n",
       "      <th>max</th>\n",
       "    </tr>\n",
       "  </thead>\n",
       "  <tbody>\n",
       "    <tr>\n",
       "      <th>Floor Level Updated</th>\n",
       "      <td>4746.0</td>\n",
       "      <td>3.445638</td>\n",
       "      <td>5.767071</td>\n",
       "      <td>0.0</td>\n",
       "      <td>1.0</td>\n",
       "      <td>2.0</td>\n",
       "      <td>3.0</td>\n",
       "      <td>76.0</td>\n",
       "    </tr>\n",
       "    <tr>\n",
       "      <th>Floor Total</th>\n",
       "      <td>4746.0</td>\n",
       "      <td>6.968605</td>\n",
       "      <td>9.467245</td>\n",
       "      <td>0.0</td>\n",
       "      <td>2.0</td>\n",
       "      <td>4.0</td>\n",
       "      <td>6.0</td>\n",
       "      <td>89.0</td>\n",
       "    </tr>\n",
       "    <tr>\n",
       "      <th>BHK</th>\n",
       "      <td>4746.0</td>\n",
       "      <td>2.083860</td>\n",
       "      <td>0.832256</td>\n",
       "      <td>1.0</td>\n",
       "      <td>2.0</td>\n",
       "      <td>2.0</td>\n",
       "      <td>3.0</td>\n",
       "      <td>6.0</td>\n",
       "    </tr>\n",
       "    <tr>\n",
       "      <th>Rent</th>\n",
       "      <td>4746.0</td>\n",
       "      <td>34993.451327</td>\n",
       "      <td>78106.412937</td>\n",
       "      <td>1200.0</td>\n",
       "      <td>10000.0</td>\n",
       "      <td>16000.0</td>\n",
       "      <td>33000.0</td>\n",
       "      <td>3500000.0</td>\n",
       "    </tr>\n",
       "    <tr>\n",
       "      <th>Size</th>\n",
       "      <td>4746.0</td>\n",
       "      <td>967.490729</td>\n",
       "      <td>634.202328</td>\n",
       "      <td>10.0</td>\n",
       "      <td>550.0</td>\n",
       "      <td>850.0</td>\n",
       "      <td>1200.0</td>\n",
       "      <td>8000.0</td>\n",
       "    </tr>\n",
       "    <tr>\n",
       "      <th>Floor</th>\n",
       "      <td>4746.0</td>\n",
       "      <td>0.001054</td>\n",
       "      <td>0.048136</td>\n",
       "      <td>0.0</td>\n",
       "      <td>0.0</td>\n",
       "      <td>0.0</td>\n",
       "      <td>0.0</td>\n",
       "      <td>3.0</td>\n",
       "    </tr>\n",
       "    <tr>\n",
       "      <th>Bathrooms</th>\n",
       "      <td>4746.0</td>\n",
       "      <td>1.965866</td>\n",
       "      <td>0.884532</td>\n",
       "      <td>1.0</td>\n",
       "      <td>1.0</td>\n",
       "      <td>2.0</td>\n",
       "      <td>2.0</td>\n",
       "      <td>10.0</td>\n",
       "    </tr>\n",
       "  </tbody>\n",
       "</table>\n",
       "</div>"
      ],
      "text/plain": [
       "                      count          mean           std     min      25%  \\\n",
       "Floor Level Updated  4746.0      3.445638      5.767071     0.0      1.0   \n",
       "Floor Total          4746.0      6.968605      9.467245     0.0      2.0   \n",
       "BHK                  4746.0      2.083860      0.832256     1.0      2.0   \n",
       "Rent                 4746.0  34993.451327  78106.412937  1200.0  10000.0   \n",
       "Size                 4746.0    967.490729    634.202328    10.0    550.0   \n",
       "Floor                4746.0      0.001054      0.048136     0.0      0.0   \n",
       "Bathrooms            4746.0      1.965866      0.884532     1.0      1.0   \n",
       "\n",
       "                         50%      75%        max  \n",
       "Floor Level Updated      2.0      3.0       76.0  \n",
       "Floor Total              4.0      6.0       89.0  \n",
       "BHK                      2.0      3.0        6.0  \n",
       "Rent                 16000.0  33000.0  3500000.0  \n",
       "Size                   850.0   1200.0     8000.0  \n",
       "Floor                    0.0      0.0        3.0  \n",
       "Bathrooms                2.0      2.0       10.0  "
      ]
     },
     "execution_count": 81,
     "metadata": {},
     "output_type": "execute_result"
    }
   ],
   "source": [
    "df.describe().T"
   ]
  },
  {
   "cell_type": "markdown",
   "id": "3e90fe12",
   "metadata": {},
   "source": [
    "- For each house, at least 1 bed, hall, and kitchen. The maximum is 6.\n",
    "- The size range varies from 550 sq ft to 8000 sq ft. \n",
    "- There are at least 1 bathroom however it can go up to 10 maximum.\n",
    "- The Floor Level Updated( originally suppose to have -2 and -1 for lower basements and floors) but it can go up to 76 floors)\n",
    "- The Floor Total starts at 0 and goes up to 89.\n",
    "- Rent can range from 1,200 to 35,000,000"
   ]
  },
  {
   "cell_type": "code",
   "execution_count": 83,
   "id": "bb0fa429",
   "metadata": {
    "scrolled": true
   },
   "outputs": [
    {
     "name": "stderr",
     "output_type": "stream",
     "text": [
      "/var/folders/5b/fvrkkcxn5x7101p1f768mrbw0000gn/T/ipykernel_23310/3698961737.py:1: FutureWarning: DataFrame.mean and DataFrame.median with numeric_only=None will include datetime64 and datetime64tz columns in a future version.\n",
      "  df.mean()\n",
      "/var/folders/5b/fvrkkcxn5x7101p1f768mrbw0000gn/T/ipykernel_23310/3698961737.py:1: FutureWarning: Dropping of nuisance columns in DataFrame reductions (with 'numeric_only=None') is deprecated; in a future version this will raise TypeError.  Select only valid columns before calling the reduction.\n",
      "  df.mean()\n"
     ]
    },
    {
     "data": {
      "text/plain": [
       "Floor Level Updated        3.445638\n",
       "Floor Total                6.968605\n",
       "BHK                        2.083860\n",
       "Rent                   34993.451327\n",
       "Size                     967.490729\n",
       "Floor                      0.001054\n",
       "Bathrooms                  1.965866\n",
       "dtype: float64"
      ]
     },
     "execution_count": 83,
     "metadata": {},
     "output_type": "execute_result"
    }
   ],
   "source": [
    "df.mean()"
   ]
  },
  {
   "cell_type": "code",
   "execution_count": 84,
   "id": "c780510d",
   "metadata": {
    "scrolled": true
   },
   "outputs": [
    {
     "name": "stderr",
     "output_type": "stream",
     "text": [
      "/var/folders/5b/fvrkkcxn5x7101p1f768mrbw0000gn/T/ipykernel_23310/530051474.py:1: FutureWarning: DataFrame.mean and DataFrame.median with numeric_only=None will include datetime64 and datetime64tz columns in a future version.\n",
      "  df.median()\n",
      "/var/folders/5b/fvrkkcxn5x7101p1f768mrbw0000gn/T/ipykernel_23310/530051474.py:1: FutureWarning: Dropping of nuisance columns in DataFrame reductions (with 'numeric_only=None') is deprecated; in a future version this will raise TypeError.  Select only valid columns before calling the reduction.\n",
      "  df.median()\n"
     ]
    },
    {
     "data": {
      "text/plain": [
       "Floor Level Updated        2.0\n",
       "Floor Total                4.0\n",
       "BHK                        2.0\n",
       "Rent                   16000.0\n",
       "Size                     850.0\n",
       "Floor                      0.0\n",
       "Bathrooms                  2.0\n",
       "dtype: float64"
      ]
     },
     "execution_count": 84,
     "metadata": {},
     "output_type": "execute_result"
    }
   ],
   "source": [
    "df.median()"
   ]
  },
  {
   "cell_type": "code",
   "execution_count": 85,
   "id": "f41eb3dd",
   "metadata": {},
   "outputs": [
    {
     "data": {
      "text/html": [
       "<div>\n",
       "<style scoped>\n",
       "    .dataframe tbody tr th:only-of-type {\n",
       "        vertical-align: middle;\n",
       "    }\n",
       "\n",
       "    .dataframe tbody tr th {\n",
       "        vertical-align: top;\n",
       "    }\n",
       "\n",
       "    .dataframe thead th {\n",
       "        text-align: right;\n",
       "    }\n",
       "</style>\n",
       "<table border=\"1\" class=\"dataframe\">\n",
       "  <thead>\n",
       "    <tr style=\"text-align: right;\">\n",
       "      <th></th>\n",
       "      <th>Floor Level Updated</th>\n",
       "      <th>Floor Total</th>\n",
       "      <th>Posted On</th>\n",
       "      <th>BHK</th>\n",
       "      <th>Rent</th>\n",
       "      <th>Size</th>\n",
       "      <th>Floor</th>\n",
       "      <th>Area Type</th>\n",
       "      <th>Area Locality</th>\n",
       "      <th>City</th>\n",
       "      <th>Furnishing Status</th>\n",
       "      <th>Tenant Preferred</th>\n",
       "      <th>Bathrooms</th>\n",
       "      <th>Point of Contact</th>\n",
       "    </tr>\n",
       "  </thead>\n",
       "  <tbody>\n",
       "    <tr>\n",
       "      <th>0</th>\n",
       "      <td>1.0</td>\n",
       "      <td>4.0</td>\n",
       "      <td>2022-07-06</td>\n",
       "      <td>2</td>\n",
       "      <td>15000</td>\n",
       "      <td>1000</td>\n",
       "      <td>0.0</td>\n",
       "      <td>Super Area</td>\n",
       "      <td>Bandra West</td>\n",
       "      <td>Mumbai</td>\n",
       "      <td>Semi-Furnished</td>\n",
       "      <td>No Preference</td>\n",
       "      <td>2</td>\n",
       "      <td>Contact Owner</td>\n",
       "    </tr>\n",
       "  </tbody>\n",
       "</table>\n",
       "</div>"
      ],
      "text/plain": [
       "   Floor Level Updated  Floor Total  Posted On  BHK   Rent  Size  Floor  \\\n",
       "0                  1.0          4.0 2022-07-06    2  15000  1000    0.0   \n",
       "\n",
       "    Area Type Area Locality    City Furnishing Status Tenant Preferred  \\\n",
       "0  Super Area   Bandra West  Mumbai    Semi-Furnished    No Preference   \n",
       "\n",
       "   Bathrooms Point of Contact  \n",
       "0          2    Contact Owner  "
      ]
     },
     "execution_count": 85,
     "metadata": {},
     "output_type": "execute_result"
    }
   ],
   "source": [
    "df.mode()"
   ]
  },
  {
   "cell_type": "markdown",
   "id": "b1db84c7",
   "metadata": {},
   "source": [
    "Above info provides the mean, median, and mode of the data set. \n",
    "\n",
    "The mean of this data set shows the Rent is much larger than the size, indicating there is a positive skew towards rent. The result also shows a positive skew towards Floor Total, which is 6. \n",
    "\n",
    "The median of the data set shows the median size is 850 sq ft, 16,000 rent, 4 floors total, 2 bathrooms, 2 floor levels and 2 bedroom,hall,and kitchen area.\n",
    "\n",
    "The mode of the data set shows it is more common to rent a house in Mumbai with 2 bathrooms, semi-furnished, no preference of tenant, 4 floors total, 1 floor level, 15,000 rent, size 1000 and the area being a super area and Bandra West.\n",
    "\n",
    "Based on the info provided, it suggests that there are positive skews towards the extremes/outliers."
   ]
  },
  {
   "cell_type": "code",
   "execution_count": 88,
   "id": "340b0a4f",
   "metadata": {},
   "outputs": [
    {
     "data": {
      "text/html": [
       "<div>\n",
       "<style scoped>\n",
       "    .dataframe tbody tr th:only-of-type {\n",
       "        vertical-align: middle;\n",
       "    }\n",
       "\n",
       "    .dataframe tbody tr th {\n",
       "        vertical-align: top;\n",
       "    }\n",
       "\n",
       "    .dataframe thead th {\n",
       "        text-align: right;\n",
       "    }\n",
       "</style>\n",
       "<table border=\"1\" class=\"dataframe\">\n",
       "  <thead>\n",
       "    <tr style=\"text-align: right;\">\n",
       "      <th></th>\n",
       "      <th>count</th>\n",
       "      <th>mean</th>\n",
       "      <th>std</th>\n",
       "      <th>min</th>\n",
       "      <th>25%</th>\n",
       "      <th>50%</th>\n",
       "      <th>75%</th>\n",
       "      <th>max</th>\n",
       "    </tr>\n",
       "  </thead>\n",
       "  <tbody>\n",
       "    <tr>\n",
       "      <th>Floor Level Updated</th>\n",
       "      <td>4746.0</td>\n",
       "      <td>3.445638</td>\n",
       "      <td>5.767071</td>\n",
       "      <td>0.0</td>\n",
       "      <td>1.0</td>\n",
       "      <td>2.0</td>\n",
       "      <td>3.0</td>\n",
       "      <td>76.0</td>\n",
       "    </tr>\n",
       "    <tr>\n",
       "      <th>Floor Total</th>\n",
       "      <td>4746.0</td>\n",
       "      <td>6.968605</td>\n",
       "      <td>9.467245</td>\n",
       "      <td>0.0</td>\n",
       "      <td>2.0</td>\n",
       "      <td>4.0</td>\n",
       "      <td>6.0</td>\n",
       "      <td>89.0</td>\n",
       "    </tr>\n",
       "    <tr>\n",
       "      <th>Floor</th>\n",
       "      <td>4746.0</td>\n",
       "      <td>0.001054</td>\n",
       "      <td>0.048136</td>\n",
       "      <td>0.0</td>\n",
       "      <td>0.0</td>\n",
       "      <td>0.0</td>\n",
       "      <td>0.0</td>\n",
       "      <td>3.0</td>\n",
       "    </tr>\n",
       "  </tbody>\n",
       "</table>\n",
       "</div>"
      ],
      "text/plain": [
       "                      count      mean       std  min  25%  50%  75%   max\n",
       "Floor Level Updated  4746.0  3.445638  5.767071  0.0  1.0  2.0  3.0  76.0\n",
       "Floor Total          4746.0  6.968605  9.467245  0.0  2.0  4.0  6.0  89.0\n",
       "Floor                4746.0  0.001054  0.048136  0.0  0.0  0.0  0.0   3.0"
      ]
     },
     "execution_count": 88,
     "metadata": {},
     "output_type": "execute_result"
    }
   ],
   "source": [
    "df.describe(include='d').T"
   ]
  },
  {
   "cell_type": "markdown",
   "id": "27a5829c",
   "metadata": {},
   "source": [
    "The floors columns show there are 89 total floors max, 76 floor level max, and 3 floors max. These results give us a better understanding of not only the amount of floors but the commonality of the different variety of floors in this dataset. "
   ]
  },
  {
   "cell_type": "code",
   "execution_count": 90,
   "id": "8d80f4ba",
   "metadata": {},
   "outputs": [
    {
     "name": "stderr",
     "output_type": "stream",
     "text": [
      "/var/folders/5b/fvrkkcxn5x7101p1f768mrbw0000gn/T/ipykernel_23310/3495979055.py:1: FutureWarning: Treating datetime data as categorical rather than numeric in `.describe` is deprecated and will be removed in a future version of pandas. Specify `datetime_is_numeric=True` to silence this warning and adopt the future behavior now.\n",
      "  df.describe(include='datetime').T\n"
     ]
    },
    {
     "data": {
      "text/html": [
       "<div>\n",
       "<style scoped>\n",
       "    .dataframe tbody tr th:only-of-type {\n",
       "        vertical-align: middle;\n",
       "    }\n",
       "\n",
       "    .dataframe tbody tr th {\n",
       "        vertical-align: top;\n",
       "    }\n",
       "\n",
       "    .dataframe thead th {\n",
       "        text-align: right;\n",
       "    }\n",
       "</style>\n",
       "<table border=\"1\" class=\"dataframe\">\n",
       "  <thead>\n",
       "    <tr style=\"text-align: right;\">\n",
       "      <th></th>\n",
       "      <th>count</th>\n",
       "      <th>unique</th>\n",
       "      <th>top</th>\n",
       "      <th>freq</th>\n",
       "      <th>first</th>\n",
       "      <th>last</th>\n",
       "    </tr>\n",
       "  </thead>\n",
       "  <tbody>\n",
       "    <tr>\n",
       "      <th>Posted On</th>\n",
       "      <td>4746</td>\n",
       "      <td>81</td>\n",
       "      <td>2022-07-06</td>\n",
       "      <td>311</td>\n",
       "      <td>2022-04-13</td>\n",
       "      <td>2022-07-11</td>\n",
       "    </tr>\n",
       "  </tbody>\n",
       "</table>\n",
       "</div>"
      ],
      "text/plain": [
       "          count unique        top freq      first       last\n",
       "Posted On  4746     81 2022-07-06  311 2022-04-13 2022-07-11"
      ]
     },
     "execution_count": 90,
     "metadata": {},
     "output_type": "execute_result"
    }
   ],
   "source": [
    "df.describe(include='datetime').T"
   ]
  },
  {
   "cell_type": "markdown",
   "id": "be33f6e7",
   "metadata": {},
   "source": [
    "The Posted On dates range from 04/13/2022 to 07/11/2022 (89 days). 81 unique values within the time span. The most common date for these listings are on 07/06/2022."
   ]
  },
  {
   "cell_type": "code",
   "execution_count": 87,
   "id": "2f72a0f7",
   "metadata": {},
   "outputs": [
    {
     "data": {
      "text/html": [
       "<div>\n",
       "<style scoped>\n",
       "    .dataframe tbody tr th:only-of-type {\n",
       "        vertical-align: middle;\n",
       "    }\n",
       "\n",
       "    .dataframe tbody tr th {\n",
       "        vertical-align: top;\n",
       "    }\n",
       "\n",
       "    .dataframe thead th {\n",
       "        text-align: right;\n",
       "    }\n",
       "</style>\n",
       "<table border=\"1\" class=\"dataframe\">\n",
       "  <thead>\n",
       "    <tr style=\"text-align: right;\">\n",
       "      <th></th>\n",
       "      <th>count</th>\n",
       "      <th>unique</th>\n",
       "      <th>top</th>\n",
       "      <th>freq</th>\n",
       "    </tr>\n",
       "  </thead>\n",
       "  <tbody>\n",
       "    <tr>\n",
       "      <th>Area Type</th>\n",
       "      <td>4746</td>\n",
       "      <td>3</td>\n",
       "      <td>Super Area</td>\n",
       "      <td>2446</td>\n",
       "    </tr>\n",
       "    <tr>\n",
       "      <th>Area Locality</th>\n",
       "      <td>4746</td>\n",
       "      <td>2235</td>\n",
       "      <td>Bandra West</td>\n",
       "      <td>37</td>\n",
       "    </tr>\n",
       "    <tr>\n",
       "      <th>City</th>\n",
       "      <td>4746</td>\n",
       "      <td>6</td>\n",
       "      <td>Mumbai</td>\n",
       "      <td>972</td>\n",
       "    </tr>\n",
       "    <tr>\n",
       "      <th>Furnishing Status</th>\n",
       "      <td>4746</td>\n",
       "      <td>3</td>\n",
       "      <td>Semi-Furnished</td>\n",
       "      <td>2251</td>\n",
       "    </tr>\n",
       "    <tr>\n",
       "      <th>Tenant Preferred</th>\n",
       "      <td>4746</td>\n",
       "      <td>3</td>\n",
       "      <td>No Preference</td>\n",
       "      <td>3444</td>\n",
       "    </tr>\n",
       "    <tr>\n",
       "      <th>Point of Contact</th>\n",
       "      <td>4746</td>\n",
       "      <td>3</td>\n",
       "      <td>Contact Owner</td>\n",
       "      <td>3216</td>\n",
       "    </tr>\n",
       "  </tbody>\n",
       "</table>\n",
       "</div>"
      ],
      "text/plain": [
       "                  count unique             top  freq\n",
       "Area Type          4746      3      Super Area  2446\n",
       "Area Locality      4746   2235     Bandra West    37\n",
       "City               4746      6          Mumbai   972\n",
       "Furnishing Status  4746      3  Semi-Furnished  2251\n",
       "Tenant Preferred   4746      3   No Preference  3444\n",
       "Point of Contact   4746      3   Contact Owner  3216"
      ]
     },
     "execution_count": 87,
     "metadata": {},
     "output_type": "execute_result"
    }
   ],
   "source": [
    "df.describe(include='object').T"
   ]
  },
  {
   "cell_type": "markdown",
   "id": "92f88776",
   "metadata": {},
   "source": [
    "For non-numerical datatypes, the counts are consistent throughout the attributes. The Area Locality stands out in the unique category as it is at 2235 while the other rows range from 3-6. The rest of the data shows what is most popular and is the same result as the mode of the dataset."
   ]
  }
 ],
 "metadata": {
  "kernelspec": {
   "display_name": "Python 3 (ipykernel)",
   "language": "python",
   "name": "python3"
  },
  "language_info": {
   "codemirror_mode": {
    "name": "ipython",
    "version": 3
   },
   "file_extension": ".py",
   "mimetype": "text/x-python",
   "name": "python",
   "nbconvert_exporter": "python",
   "pygments_lexer": "ipython3",
   "version": "3.9.12"
  }
 },
 "nbformat": 4,
 "nbformat_minor": 5
}
